MANIFEST.in
README.md
setup.py
opp_frontend/__init__.py
opp_frontend/authorize.html
opp_frontend/index.html
opp_frontend/onboarding.html
opp_frontend/robots.txt
opp_frontend/service_worker.js
opp_frontend/frontend_latest/0.chunk.js
opp_frontend/frontend_latest/1.chunk.js
opp_frontend/frontend_latest/10.chunk.js
opp_frontend/frontend_latest/11.chunk.js
opp_frontend/frontend_latest/12.chunk.js
opp_frontend/frontend_latest/13.chunk.js
opp_frontend/frontend_latest/14.chunk.js
opp_frontend/frontend_latest/15.chunk.js
opp_frontend/frontend_latest/16.chunk.js
opp_frontend/frontend_latest/17.chunk.js
opp_frontend/frontend_latest/18.chunk.js
opp_frontend/frontend_latest/19.chunk.js
opp_frontend/frontend_latest/2.chunk.js
opp_frontend/frontend_latest/20.chunk.js
opp_frontend/frontend_latest/21.chunk.js
opp_frontend/frontend_latest/218acaa6010915001ec1.worker.js
opp_frontend/frontend_latest/22.chunk.js
opp_frontend/frontend_latest/23.chunk.js
opp_frontend/frontend_latest/24.chunk.js
opp_frontend/frontend_latest/25.chunk.js
opp_frontend/frontend_latest/26.chunk.js
opp_frontend/frontend_latest/27.chunk.js
opp_frontend/frontend_latest/28.chunk.js
opp_frontend/frontend_latest/3.chunk.js
opp_frontend/frontend_latest/4.chunk.js
opp_frontend/frontend_latest/5.chunk.js
opp_frontend/frontend_latest/6.chunk.js
opp_frontend/frontend_latest/7.chunk.js
opp_frontend/frontend_latest/74974920fa390243d7d6.worker.js
opp_frontend/frontend_latest/8.chunk.js
opp_frontend/frontend_latest/9.chunk.js
opp_frontend/frontend_latest/app.js
opp_frontend/frontend_latest/area-registry-detail-dialog.chunk.js
opp_frontend/frontend_latest/authorize.js
opp_frontend/frontend_latest/cloud-alexa.chunk.js
opp_frontend/frontend_latest/cloud-alexa~cloud-google-assistant.chunk.js
opp_frontend/frontend_latest/cloud-forgot-password.chunk.js
opp_frontend/frontend_latest/cloud-google-assistant.chunk.js
opp_frontend/frontend_latest/cloud-register.chunk.js
opp_frontend/frontend_latest/cloud-webhook-manage-dialog.chunk.js
opp_ui.egg-info/PKG-INFO
opp_ui.egg-info/SOURCES.txt
opp_ui.egg-info/dependency_links.txt
opp_ui.egg-info/not-zip-safe
opp_ui.egg-info/top_level.txt