Metadata-Version: 1.2
Name: opp-ui
Version: 0.1.0
Summary: The Open Peer Power user interface
Home-page: https://OpenPeerPower.io/
Author: Paul Caston
Author-email: paul@caston.id.au
License: Apache License 2.0
Project-URL: Bug Reports, https://github.com/OpenPeerPower/OPP-ui/issues
Platform: UNKNOWN
